pycouchdb/__init__.py
pycouchdb/client.py
pycouchdb/exceptions.py
pycouchdb/feedreader.py
pycouchdb/resource.py
pycouchdb/utils.py
pycouchdb-1.14.2.dist-info/LICENSE
pycouchdb-1.14.2.dist-info/WHEEL
pycouchdb-1.14.2.dist-info/METADATA
pycouchdb-1.14.2.dist-info/RECORD
