Metadata-Version: 2.1
Name: pycouchdb
Version: 1.14.2
Summary: Modern pure python CouchDB Client.
Home-page: https://github.com/histrio/py-couchdb
License: BSD-3-Clause
Keywords: couchdb,database
Author: Andrey Antukh
Author-email: niwi@niwi.be
Maintainer: Rinat Sabitov
Maintainer-email: rinat.sabitov@gmail.com
Requires-Python: >=2.7, !=3.0.*, !=3.1.*, !=3.2.*, !=3.3.*, !=3.4.*, !=3.5.*
Classifier: License :: OSI Approved :: BSD License
Classifier: Programming Language :: Python :: 2
Classifier: Programming Language :: Python :: 2.7
Classifier: Programming Language :: Python :: 3
Classifier: Programming Language :: Python :: 3.10
Classifier: Programming Language :: Python :: 3.6
Classifier: Programming Language :: Python :: 3.7
Classifier: Programming Language :: Python :: 3.8
Classifier: Programming Language :: Python :: 3.9
Classifier: Topic :: Software Development :: Libraries :: Python Modules
Classifier: Topic :: Utilities
Requires-Dist: requests (>=2.25,<3.0)
Project-URL: Documentation, https://pycouchdb.readthedocs.io/en/latest/
Project-URL: Repository, https://github.com/histrio/py-couchdb
